{
  "employees": [
    {
      "employee_id": "emp_001",
      "name": "John Doe",
      "id_number": "123456789",
      "department": null,
      "position": null,
      "start_date": "2023-01-01",
      "employment_type": "full_time",
      "created_date": "2025-08-26 06:51:52.627638",
      "updated_date": "2025-08-26 06:51:52.627691",
      "alternative_names": [],
      "correlation_confidence": 1.0
    },
    {
      "employee_id": "emp_8173",
      "name": "Employee emp_8173",
      "id_number": "000000000",
      "department": null,
      "position": null,
      "start_date": null,
      "employment_type": "full_time",
      "created_date": "2025-08-26 07:53:05.612835",
      "updated_date": "2025-08-26 07:53:05.612840",
      "alternative_names": [],
      "correlation_confidence": 1.0
    }
  ],
  "metadata": {
    "created_date": "2024-01-01T00:00:00",
    "last_updated": "2024-01-01T00:00:00",
    "version": "1.0"
  }
}